shlesha-0.5.4.dist-info/METADATA
shlesha-0.5.4.dist-info/WHEEL
shlesha-0.5.4.dist-info/licenses/LICENSE
shlesha/__init__.py
shlesha/shlesha.cp39-win_amd64.pyd
shlesha-0.5.4.dist-info/RECORD
