Metadata-Version: 2.4
Name: shlesha
Version: 0.5.4
Classifier: Development Status :: 4 - Beta
Classifier: Intended Audience :: Developers
Classifier: Intended Audience :: Science/Research
Classifier: License :: OSI Approved :: MIT License
Classifier: License :: OSI Approved :: Apache Software License
Classifier: Programming Language :: Python :: 3
Classifier: Programming Language :: Python :: 3.9
Classifier: Programming Language :: Python :: 3.10
Classifier: Programming Language :: Python :: 3.11
Classifier: Programming Language :: Python :: 3.12
Classifier: Programming Language :: Python :: 3.13
Classifier: Programming Language :: Rust
Classifier: Topic :: Text Processing :: Linguistic
Classifier: Topic :: Software Development :: Libraries :: Python Modules
Requires-Dist: pytest>=6.0 ; extra == 'dev'
Requires-Dist: pytest-benchmark>=3.4 ; extra == 'dev'
Requires-Dist: maturin>=1.0,<2.0 ; extra == 'dev'
Requires-Dist: pytest>=6.0 ; extra == 'test'
Requires-Dist: pytest-asyncio>=0.20.0 ; extra == 'test'
Requires-Dist: sphinx>=4.0 ; extra == 'docs'
Requires-Dist: sphinx-rtd-theme>=1.0 ; extra == 'docs'
Provides-Extra: dev
Provides-Extra: test
Provides-Extra: docs
License-File: LICENSE
Summary: High-performance extensible transliteration library for Sanskrit and Indic scripts
Keywords: transliteration,sanskrit,indic,devanagari,unicode
Author: udapaana
License: MIT OR Apache-2.0
Requires-Python: >=3.9
Project-URL: homepage, https://github.com/udapaana/shlesha
Project-URL: repository, https://github.com/udapaana/shlesha
Project-URL: documentation, https://github.com/udapaana/shlesha/blob/main/README.md
